packer/__init__.py
packer/cli.py
packer/errors.py
packer/formatters/__init__.py
packer/formatters/base.py
packer/formatters/json_formatter.py
packer/formatters/yaml_formatter.py
packer_cli-0.7.0.dist-info/DESCRIPTION.rst
packer_cli-0.7.0.dist-info/METADATA
packer_cli-0.7.0.dist-info/RECORD
packer_cli-0.7.0.dist-info/WHEEL
packer_cli-0.7.0.dist-info/entry_points.txt
packer_cli-0.7.0.dist-info/metadata.json
packer_cli-0.7.0.dist-info/top_level.txt
