Metadata-Version: 2.0
Name: packer-cli
Version: 0.7.0
Summary: Command line utility for converting data to different formats
Home-page: https://github.com/durandj/packer
Author: James Durand
Author-email: james.durand@alumni.msoe.edu
License: MIT license
Keywords: packer
Platform: UNKNOWN
Classifier: Development Status :: 2 - Pre-Alpha
Classifier: Intended Audience :: Developers
Classifier: License :: OSI Approved :: MIT License
Classifier: Natural Language :: English
Classifier: Programming Language :: Python :: 3.6
Requires-Dist: PyYaml (==3.12)
Requires-Dist: click (==6.7)
